pyq3serverlist/__init__.py
pyq3serverlist/buffer.py
pyq3serverlist/connection.py
pyq3serverlist/exceptions.py
pyq3serverlist/logger.py
pyq3serverlist/principalserver.py
pyq3serverlist/reader.py
pyq3serverlist/server.py
pyq3serverlist-0.4.0.dist-info/licenses/LICENSE.md
pyq3serverlist-0.4.0.dist-info/METADATA
pyq3serverlist-0.4.0.dist-info/WHEEL
pyq3serverlist-0.4.0.dist-info/top_level.txt
pyq3serverlist-0.4.0.dist-info/RECORD
