Metadata-Version: 2.4
Name: pyq3serverlist
Version: 0.4.0
Summary: Simple Python library for querying Quake 3 based principal servers and their game servers
Home-page: https://github.com/cetteup/pyq3serverlist
Author: cetteup
Author-email: me@cetteup.com
License: MIT
Project-URL: Bug Tracker, https://github.com/cetteup/pyq3serverlist/issues
Classifier: Development Status :: 4 - Beta
Classifier: Intended Audience :: Developers
Classifier: License :: OSI Approved :: MIT License
Classifier: Operating System :: OS Independent
Classifier: Programming Language :: Python :: 3
Requires-Python: >=3.9
License-File: LICENSE.md
Dynamic: license-file
